bio2bel_famplex/__init__.py
bio2bel_famplex/__main__.py
bio2bel_famplex/cli.py
bio2bel_famplex/constants.py
bio2bel_famplex/equivalences.py
bio2bel_famplex/manager.py
bio2bel_famplex/relations.py
bio2bel_famplex-0.0.1.dist-info/LICENSE
bio2bel_famplex-0.0.1.dist-info/METADATA
bio2bel_famplex-0.0.1.dist-info/WHEEL
bio2bel_famplex-0.0.1.dist-info/entry_points.txt
bio2bel_famplex-0.0.1.dist-info/top_level.txt
bio2bel_famplex-0.0.1.dist-info/RECORD
