Metadata-Version: 2.1
Name: bio2bel-famplex
Version: 0.0.1
Summary: Downloader, parser, and BEL converter for FamPlex
Home-page: https://github.com/bio2bel/famplex
Author: Kristian Kolpeja and Charles Tapley Hoyt
Author-email: charles.hoyt@scai.fraunhofer.de
Maintainer: Charles Tapley Hoyt
Maintainer-email: charles.hoyt@scai.fraunhofer.de
License: MIT
Keywords: Biological Expression Language,Systems Biology,Protein Families,Protein Complexes
Platform: UNKNOWN
Classifier: Development Status :: 1 - Planning
Classifier: Intended Audience :: Developers
Classifier: Programming Language :: Python
Classifier: Programming Language :: Python :: 3.7
Classifier: Programming Language :: Python :: 3.6
Classifier: Programming Language :: Python :: 3 :: Only
Classifier: License :: OSI Approved :: MIT License
Requires-Python: >=3.6
Requires-Dist: click
Requires-Dist: pandas
Requires-Dist: pybel
Requires-Dist: bio2bel
Provides-Extra: docs
Requires-Dist: sphinx ; extra == 'docs'
Requires-Dist: sphinx-rtd-theme ; extra == 'docs'
Requires-Dist: sphinx-click ; extra == 'docs'
Requires-Dist: sphinx-autodoc-typehints ; extra == 'docs'
